bits3/__init__.py
bits3/cli.py
bits3/core.py
bits3/utils.py
bits3-0.1.dist-info/AUTHORS.rst
bits3-0.1.dist-info/LICENSE.txt
bits3-0.1.dist-info/METADATA
bits3-0.1.dist-info/WHEEL
bits3-0.1.dist-info/entry_points.txt
bits3-0.1.dist-info/top_level.txt
bits3-0.1.dist-info/RECORD
