Metadata-Version: 2.1
Name: bits3
Version: 0.1
Summary: Upload Backintime snapshots to AWS S3.
Home-page: https://github.com/hille721/bits3/
Author: Christoph Hille
Author-email: hille721@gmail.com
License: MIT License
Project-URL: Documentation, https://github.com/hille721/bits3/
Platform: Linux
Classifier: Development Status :: 4 - Beta
Classifier: Programming Language :: Python
Classifier: Programming Language :: Python :: 3
Classifier: Programming Language :: Python :: 3.6
Classifier: Programming Language :: Python :: 3.7
Classifier: Programming Language :: Python :: 3.8
Classifier: Operating System :: POSIX :: Linux
Classifier: License :: OSI Approved :: MIT License
Requires-Dist: boto3
Requires-Dist: click
